nitrotype/__init__.py
nitrotype/_news.py
nitrotype/_nitromath.py
nitrotype/_nitromathteam.py
nitrotype/_nitrotype.py
nitrotype/_nitrotypeteam.py
NitroPy-1.2.1.dist-info/METADATA
NitroPy-1.2.1.dist-info/WHEEL
NitroPy-1.2.1.dist-info/top_level.txt
NitroPy-1.2.1.dist-info/RECORD
