Metadata-Version: 2.1
Name: NitroPy
Version: 1.2.1
Summary: A package for interacting with the website, Nitrotype and Nitromath
Author: Malakai
Author-email: Almightyslider2@gmail.com
Classifier: Programming Language :: Python :: 3
Classifier: License :: OSI Approved :: MIT License
Classifier: Operating System :: OS Independent
Requires-Python: >=3.6
Requires-Dist: cloudscraper
Requires-Dist: beautifulsoup4
Requires-Dist: twine
